LICENSE
xbridge_cli/__init__.py
xbridge_cli/bridge/__init__.py
xbridge_cli/bridge/build.py
xbridge_cli/bridge/create_account.py
xbridge_cli/bridge/register.py
xbridge_cli/bridge/transfer.py
xbridge_cli/exceptions.py
xbridge_cli/main.py
xbridge_cli/misc/__init__.py
xbridge_cli/misc/explorer.html
xbridge_cli/misc/explorer.py
xbridge_cli/misc/fund.py
xbridge_cli/misc/trust.py
xbridge_cli/server/__init__.py
xbridge_cli/server/config/__init__.py
xbridge_cli/server/config/config.py
xbridge_cli/server/config/ports.py
xbridge_cli/server/config/templates/bootstrap.jinja
xbridge_cli/server/config/templates/rippled.jinja
xbridge_cli/server/config/templates/witness.jinja
xbridge_cli/server/docker-compose.yml
xbridge_cli/server/list.py
xbridge_cli/server/print.py
xbridge_cli/server/request.py
xbridge_cli/server/restart.py
xbridge_cli/server/start.py
xbridge_cli/server/stop.py
xbridge_cli/utils/__init__.py
xbridge_cli/utils/attestations.py
xbridge_cli/utils/config_file/__init__.py
xbridge_cli/utils/config_file/bridge_config.py
xbridge_cli/utils/config_file/chain_config.py
xbridge_cli/utils/config_file/config_file.py
xbridge_cli/utils/config_file/config_item.py
xbridge_cli/utils/config_file/server_config.py
xbridge_cli/utils/config_file/witness_config.py
xbridge_cli/utils/config_utils.py
xbridge_cli/utils/misc.py
xbridge_cli/utils/rippled_config.py
xbridge_cli/utils/transaction.py
xbridge_cli/utils/types.py
xbridge_cli-0.3.3.dist-info/LICENSE
xbridge_cli-0.3.3.dist-info/METADATA
xbridge_cli-0.3.3.dist-info/WHEEL
xbridge_cli-0.3.3.dist-info/entry_points.txt
xbridge_cli-0.3.3.dist-info/RECORD
